JavaGongchengshiShiliCankaoshouceLiaoQingyuan/README.md
JavaGongchengshiShiliCankaoshouceLiaoQingyuan/__init__.py
JavaGongchengshiShiliCankaoshouceLiaoQingyuan/__main__.py
JavaGongchengshiShiliCankaoshouceLiaoQingyuan/file.pdf
JavaGongchengshiShiliCankaoshouceLiaoQingyuan/index.html
java_gongchengshi_shili_cankaoshouce_liao_qingyuan-2024.3.2.0.dist-info/METADATA
java_gongchengshi_shili_cankaoshouce_liao_qingyuan-2024.3.2.0.dist-info/WHEEL
java_gongchengshi_shili_cankaoshouce_liao_qingyuan-2024.3.2.0.dist-info/entry_points.txt
java_gongchengshi_shili_cankaoshouce_liao_qingyuan-2024.3.2.0.dist-info/top_level.txt
java_gongchengshi_shili_cankaoshouce_liao_qingyuan-2024.3.2.0.dist-info/RECORD
